hubble_exchange/__init__.py
hubble_exchange/client.py
hubble_exchange/constants.py
hubble_exchange/errors.py
hubble_exchange/eth.py
hubble_exchange/indexer_client.py
hubble_exchange/models.py
hubble_exchange/order_book.py
hubble_exchange/utils.py
hubble_exchange/config/__init__.py
hubble_exchange/config/aylin.py
hubble_exchange/config/hubblenext.py
hubble_exchange/config/local.py
hubble_exchange/config/mainnet.py
hubble_exchange/contract_abis/AMM.json
hubble_exchange/contract_abis/ClearingHouse.json
hubble_exchange/contract_abis/HGT.json
hubble_exchange/contract_abis/HGTRemote.json
hubble_exchange/contract_abis/IERC20.json
hubble_exchange/contract_abis/ImmediateOrCancelOrders.json
hubble_exchange/contract_abis/LimitOrderBook.json
hubble_exchange/contract_abis/MarginAccountHelper.json
hubble_exchange/contract_abis/OrderBook.json
hubble_exchange-0.8.8.dist-info/LICENSE
hubble_exchange-0.8.8.dist-info/METADATA
hubble_exchange-0.8.8.dist-info/WHEEL
hubble_exchange-0.8.8.dist-info/top_level.txt
hubble_exchange-0.8.8.dist-info/RECORD
