Metadata-Version: 2.1
Name: hubble-exchange
Version: 0.8.8
Summary: Official python SDK for Hubble Exchange
Author-email: Lumos <lumos@hubble.exchange>
License: MIT License
Project-URL: homepage, https://github.com/hubble-exchange/python-sdk
Keywords: hubble,exchange,orderbook,perpetual,futures,dex,sdk,python,avalanche,ethereum,web3,crypto
Requires-Python: >=3.7
License-File: LICENSE
Requires-Dist: web3 >=6.5.0
Requires-Dist: eth-typing >=3.4.0
Requires-Dist: eth-account >=0.8.0
Requires-Dist: requests >=2.31.0
